tests/__init__.py
tests/test_download.py
tests/timeout.py
tests/test_pairs.py
tests/test_granules.py
tests/test_download_pairs.py
asf_granule_util/__init__.py
asf_granule_util/pairs.py
asf_granule_util/download.py
asf_granule_util/granules.py
asf_granule_util/exceptions.py
asf_granule_util/stack.py
asf_granule_util-0.0.62.dist-info/metadata.json
asf_granule_util-0.0.62.dist-info/RECORD
asf_granule_util-0.0.62.dist-info/METADATA
asf_granule_util-0.0.62.dist-info/WHEEL
asf_granule_util-0.0.62.dist-info/DESCRIPTION.rst
asf_granule_util-0.0.62.dist-info/top_level.txt
