Metadata-Version: 2.0
Name: asf-granule-util
Version: 0.0.62
Summary: Library for handling sentinel granules
Home-page: http://asf-docs.s3-website-us-west-2.amazonaws.com/asf-granule-util/
Author: ASF Student Development Team 2017
Author-email: eng.accts@asf.alaska.edu
License: 'License :: OSI Approved :: MIT License'
Keywords: granule asf sentinel-1 util
Platform: UNKNOWN
Classifier: Development Status :: 3 - Alpha
Classifier: Intended Audience :: Science/Research
Classifier: Topic :: Scientific/Engineering :: GIS
Classifier: Programming Language :: Python :: 2.7
Classifier: Programming Language :: Python :: 3
Requires-Dist: certifi (==2018.8.13)
Requires-Dist: chardet (==3.0.4)
Requires-Dist: idna (==2.7)
Requires-Dist: requests (==2.19.1)
Requires-Dist: tqdm (==4.24.0)
Requires-Dist: urllib3 (==1.23)
